flask_compress.py
setup.py
Flask_Compress_nondebug.egg-info/PKG-INFO
Flask_Compress_nondebug.egg-info/SOURCES.txt
Flask_Compress_nondebug.egg-info/dependency_links.txt
Flask_Compress_nondebug.egg-info/not-zip-safe
Flask_Compress_nondebug.egg-info/requires.txt
Flask_Compress_nondebug.egg-info/top_level.txt